orange_earth_observation-1.1.1-py3.8-nspkg.pth
orangecontrib/earth_observation/__init__.py
orangecontrib/earth_observation/_version.py
orangecontrib/earth_observation/widgets/__init__.py
orangecontrib/earth_observation/widgets/catalog.py
orangecontrib/earth_observation/widgets/cloud_mask.py
orangecontrib/earth_observation/widgets/crop_image.py
orangecontrib/earth_observation/widgets/geoserver.py
orangecontrib/earth_observation/widgets/histogram.py
orangecontrib/earth_observation/widgets/index_calculation.py
orangecontrib/earth_observation/widgets/load_image.py
orangecontrib/earth_observation/widgets/manifest.py
orangecontrib/earth_observation/widgets/mosaic_image.py
orangecontrib/earth_observation/widgets/nuts_shape.py
orangecontrib/earth_observation/widgets/reproject_image.py
orangecontrib/earth_observation/widgets/rgb_calculation.py
orangecontrib/earth_observation/widgets/utils.py
orangecontrib/earth_observation/widgets/view_image.py
orangecontrib/earth_observation/widgets/icons/calculate.svg
orangecontrib/earth_observation/widgets/icons/catalog.svg
orangecontrib/earth_observation/widgets/icons/category.svg
orangecontrib/earth_observation/widgets/icons/cloud.svg
orangecontrib/earth_observation/widgets/icons/crop.svg
orangecontrib/earth_observation/widgets/icons/geoserver.svg
orangecontrib/earth_observation/widgets/icons/histogram.svg
orangecontrib/earth_observation/widgets/icons/load.svg
orangecontrib/earth_observation/widgets/icons/manifest.svg
orangecontrib/earth_observation/widgets/icons/mosaic.svg
orangecontrib/earth_observation/widgets/icons/nuts.svg
orangecontrib/earth_observation/widgets/icons/projection.svg
orangecontrib/earth_observation/widgets/icons/view.svg
orange_earth_observation-1.1.1.dist-info/METADATA
orange_earth_observation-1.1.1.dist-info/WHEEL
orange_earth_observation-1.1.1.dist-info/entry_points.txt
orange_earth_observation-1.1.1.dist-info/namespace_packages.txt
orange_earth_observation-1.1.1.dist-info/top_level.txt
orange_earth_observation-1.1.1.dist-info/RECORD
