Metadata-Version: 2.1
Name: orange-earth-observation
Version: 1.1.1
Summary: Add-on containing widgets for earth observation data operations
Home-page: https://gitlab.com/drb-python/samples/odm/eo_addon
Author: GAEL Systems
Author-email: drb-python@gael.fr
License: LGPLv3
Classifier: Programming Language :: Python :: 3.8
Classifier: Environment :: Plugins
Classifier: License :: OSI Approved :: GNU Lesser General Public License v3 (LGPLv3)
Requires-Python: >=3.8
Requires-Dist: drb (~=2.0.3)
Requires-Dist: drb-driver-odata (~=1.1.0)
Requires-Dist: drb-driver-file (~=1.1.0)
Requires-Dist: drb-driver-image (~=1.1.1)
Requires-Dist: drb-driver-zip (~=1.1.0)
Requires-Dist: numpy (>=1.23.4)
Requires-Dist: nums-from-string (>=0.1.2)
Requires-Dist: pyshp (>=2.3.1)
Requires-Dist: folium (>=0.13.0)
Requires-Dist: rasterio (>=1.3.2)
Requires-Dist: opencv-python (>=4.6.0.66)
Requires-Dist: matplotlib (~=3.5.2)
Requires-Dist: scikit-image (>=0.19.3)
